MANIFEST.in
setup.py
example/__init__.py
example/api_call.py
example/api_call_t.py
example/quick_start.py
example/singleton.py
example/t_decorater.py
example/t_temp.py
example/t_wamp.py
example/t_warmp.py
fangcloud_sdk.egg-info/PKG-INFO
fangcloud_sdk.egg-info/SOURCES.txt
fangcloud_sdk.egg-info/dependency_links.txt
fangcloud_sdk.egg-info/requires.txt
fangcloud_sdk.egg-info/top_level.txt
fangcloudsdk/__init__.py
fangcloudsdk/adapt.py
fangcloudsdk/base_httpclient.py
fangcloudsdk/base_object.py
fangcloudsdk/client.py
fangcloudsdk/config.py
fangcloudsdk/exception.py
fangcloudsdk/file.py
fangcloudsdk/folder.py
fangcloudsdk/item.py
fangcloudsdk/logger.py
fangcloudsdk/oauth.py
fangcloudsdk/request_client.py
fangcloudsdk/request_route.py
fangcloudsdk/status_code.py
fangcloudsdk/urltemplate.py
fangcloudsdk/user.py
fangcloudsdk/util.py
test/__init__.py
test/global_test_config.py
test/t_file.py
test/t_folder.py
test/t_item.py
test/t_oauth.py
test/t_thread_request.py
test/t_user.py