Metadata-Version: 1.0
Name: fangcloud-sdk
Version: 0.0.3
Summary: This is fangcloud open platform python sdk
Home-page: http://www.fangcloud.com
Author: FangCloud
Author-email: 1743159479@qq.com
License: Apache Software License, Version 2.0,http://www.apache.org/licenses/LICENSE-2.0
Keywords: fangcloud,sdk,open,platform
Platform: any
